pyavl3/__init__.py
pyavl3/avl_node.py
pyavl3/avl_tree.py
pyavl3/interface.py
pyavl3/search.py
pyavl3/traversal.py
pyavl3-1.0.0.dist-info/LICENSE
pyavl3-1.0.0.dist-info/METADATA
pyavl3-1.0.0.dist-info/WHEEL
pyavl3-1.0.0.dist-info/top_level.txt
pyavl3-1.0.0.dist-info/RECORD
