Metadata-Version: 2.1
Name: pyavl3
Version: 1.0.0
Summary: Pure python implementation of avl trees.
Home-page: https://github.com/en0/pyavl3
Author: Ian Laird
Author-email: irlaird@gmail.com
License: MIT
Keywords: avl,avltree,balancedtree,bst
Platform: UNKNOWN
Classifier: Programming Language :: Python :: 3
Classifier: License :: OSI Approved :: MIT License
Classifier: Operating System :: OS Independent
